tanml/__init__.py
tanml/check_runners/__init__.py
tanml/check_runners/base_runner.py
tanml/check_runners/cleaning_repro_runner.py
tanml/check_runners/correlation_runner.py
tanml/check_runners/data_quality_runner.py
tanml/check_runners/eda_runner.py
tanml/check_runners/explainability_runner.py
tanml/check_runners/input_cluster_runner.py
tanml/check_runners/logistic_stats_runner.py
tanml/check_runners/model_meta_runner.py
tanml/check_runners/performance_runner.py
tanml/check_runners/raw_data_runner.py
tanml/check_runners/regression_metrics_runner.py
tanml/check_runners/rule_engine_runner.py
tanml/check_runners/stress_test_runner.py
tanml/check_runners/vif_runner.py
tanml/checks/__init__.py
tanml/checks/base.py
tanml/checks/cleaning_repro.py
tanml/checks/correlation.py
tanml/checks/data_quality.py
tanml/checks/eda.py
tanml/checks/input_cluster.py
tanml/checks/logit_stats.py
tanml/checks/model_contents.py
tanml/checks/model_meta.py
tanml/checks/performance.py
tanml/checks/performance_classification.py
tanml/checks/raw_data.py
tanml/checks/regression_metrics.py
tanml/checks/rule_engine.py
tanml/checks/stress_test.py
tanml/checks/vif.py
tanml/checks/explainability/shap_check.py
tanml/cli/__init__.py
tanml/cli/main.py
tanml/config_templates/__init__.py
tanml/engine/__init__.py
tanml/engine/check_agent_registry.py
tanml/engine/core_engine_agent.py
tanml/models/registry.py
tanml/report/report_builder.py
tanml/report/templates/report_template_cls.docx
tanml/report/templates/report_template_reg.docx
tanml/ui/app.py
tanml/utils/__init__.py
tanml/utils/data_loader.py
tanml-0.1.7.dist-info/licenses/LICENSE
tanml-0.1.7.dist-info/METADATA
tanml-0.1.7.dist-info/WHEEL
tanml-0.1.7.dist-info/entry_points.txt
tanml-0.1.7.dist-info/top_level.txt
tanml-0.1.7.dist-info/RECORD
