Metadata-Version: 2.4
Name: tanml
Version: 0.1.7
Summary: Automated validation toolkit for tabular ML models—MRM, credit risk, insurance, and other regulated use cases.
Author: Tanmay Sah, Dolly Sah
Maintainer: Tanmay Sah, Dolly Sah
License-Expression: MIT
Project-URL: Homepage, https://github.com/tdlabs-ai/tanml
Project-URL: Source, https://github.com/tdlabs-ai/tanml
Project-URL: Issues, https://github.com/tdlabs-ai/tanml/issues
Project-URL: Documentation, https://github.com/tdlabs-ai/tanml#readme
Keywords: model validation,model risk management,model governance,SR 11-7,tabular ML,credit risk,insurance analytics,explainability,XAI,SHAP,stress testing,reporting,docx,streamlit,xgboost,lightgbm,catboost
Classifier: Development Status :: 4 - Beta
Classifier: Intended Audience :: Science/Research
Classifier: Intended Audience :: Financial and Insurance Industry
Classifier: Natural Language :: English
Classifier: Operating System :: OS Independent
Classifier: Programming Language :: Python
Classifier: Programming Language :: Python :: 3
Classifier: Programming Language :: Python :: 3 :: Only
Classifier: Programming Language :: Python :: 3.8
Classifier: Programming Language :: Python :: 3.9
Classifier: Programming Language :: Python :: 3.10
Classifier: Programming Language :: Python :: 3.11
Classifier: Programming Language :: Python :: 3.12
Classifier: Topic :: Scientific/Engineering :: Artificial Intelligence
Classifier: Topic :: Scientific/Engineering :: Information Analysis
Classifier: Topic :: Scientific/Engineering :: Visualization
Requires-Python: >=3.8
License-File: LICENSE
Requires-Dist: numpy>=1.26
Requires-Dist: scipy>=1.11
Requires-Dist: pandas>=2.0
Requires-Dist: scikit-learn>=1.3
Requires-Dist: statsmodels>=0.14
Requires-Dist: xgboost>=2.0
Requires-Dist: lightgbm>=4.3
Requires-Dist: catboost>=1.2
Requires-Dist: shap>=0.44
Requires-Dist: numba>=0.58
Requires-Dist: matplotlib>=3.8
Requires-Dist: seaborn>=0.13
Requires-Dist: Pillow>=10.0
Requires-Dist: python-docx>=1.1.2
Requires-Dist: tzlocal>=5.0
Requires-Dist: tqdm>=4.66
Requires-Dist: pyarrow>=14.0
Requires-Dist: openpyxl>=3.1
Requires-Dist: pyreadstat>=1.2
Requires-Dist: streamlit>=1.36
Provides-Extra: dev
Requires-Dist: pytest; extra == "dev"
Requires-Dist: black; extra == "dev"
Requires-Dist: isort; extra == "dev"
Dynamic: license-file
